[
    {
        "id": 1,
        "label": "A1",
        "location": "",
        "created_at": "2019-01-23T07:56:43.480Z",
        "updated_at": "2019-01-23T07:56:43.480Z",
        "url": "http://apac-ar-test.herokuapp.com/desks/1.json"
    },
    {
        "id": 2,
        "label": "A2",
        "location": "",
        "created_at": "2019-01-23T07:56:51.122Z",
        "updated_at": "2019-01-23T07:56:51.122Z",
        "url": "http://apac-ar-test.herokuapp.com/desks/2.json"
    },
    {
        "id": 3,
        "label": "A3",
        "location": "",
        "created_at": "2019-01-23T07:56:59.414Z",
        "updated_at": "2019-01-23T07:56:59.414Z",
        "url": "http://apac-ar-test.herokuapp.com/desks/3.json"
    },
    {
        "id": 4,
        "label": "A4",
        "location": "",
        "created_at": "2019-01-23T07:57:07.754Z",
        "updated_at": "2019-01-23T07:57:07.754Z",
        "url": "http://apac-ar-test.herokuapp.com/desks/4.json"
    }
]